ai_agent_deployer/__init__.py
ai_agent_deployer/core/deployer.py
ai_agent_deployer-0.1.dist-info/METADATA
ai_agent_deployer-0.1.dist-info/WHEEL
ai_agent_deployer-0.1.dist-info/RECORD
